motoko_cli/__about__.py
motoko_cli/__init__.py
motoko_cli-0.0.5.dist-info/METADATA
motoko_cli-0.0.5.dist-info/WHEEL
motoko_cli-0.0.5.dist-info/licenses/LICENSE
motoko_cli-0.0.5.dist-info/RECORD
