Metadata-Version: 2.4
Name: motoko-cli
Version: 0.0.5
Project-URL: Documentation, https://github.com/motOko/motoko-cli#readme
Project-URL: Issues, https://github.com/motOko/motoko-cli/issues
Project-URL: Source, https://github.com/motOko/motoko-cli
Author-email: motOko <dourval.clement@gmail.com>
License-Expression: MIT
License-File: LICENSE
Classifier: Development Status :: 4 - Beta
Classifier: Programming Language :: Python
Classifier: Programming Language :: Python :: 3.8
Classifier: Programming Language :: Python :: 3.9
Classifier: Programming Language :: Python :: 3.10
Classifier: Programming Language :: Python :: 3.11
Classifier: Programming Language :: Python :: 3.12
Classifier: Programming Language :: Python :: Implementation :: CPython
Classifier: Programming Language :: Python :: Implementation :: PyPy
Requires-Python: >=3.8
